smoothcache/__init__.py
smoothcache/exceptions.py
smoothcache/smooth.py
smoothcache-1.1.0.dist-info/LICENSE
smoothcache-1.1.0.dist-info/METADATA
smoothcache-1.1.0.dist-info/WHEEL
smoothcache-1.1.0.dist-info/top_level.txt
smoothcache-1.1.0.dist-info/RECORD
