Metadata-Version: 2.1
Name: smoothcache
Version: 1.1.0
Summary: Simple, in-memory, thread-safe caching system for python programs.
Author-email: Mason Weaver <mason@swingproxy.com>
Project-URL: Homepage, https://github.com/Otach/smoothcache
Keywords: cache
Classifier: Programming Language :: Python :: 3
Classifier: License :: OSI Approved :: MIT License
Classifier: Operating System :: OS Independent
Requires-Python: >=3.8
License-File: LICENSE
